check_nginx_status/__init__.py
check_nginx_status/check_nginx_status.py
check_nginx_status-1.0.0.dist-info/LICENSE
check_nginx_status-1.0.0.dist-info/METADATA
check_nginx_status-1.0.0.dist-info/WHEEL
check_nginx_status-1.0.0.dist-info/top_level.txt
check_nginx_status-1.0.0.dist-info/RECORD
