Metadata-Version: 2.1
Name: check-nginx-status
Version: 1.0.0
Summary: Script to check nginx status
Home-page: https://gitlab.ics.muni.cz/perun-proxy-aai/python/check_nginx_status.git
License: UNKNOWN
Platform: UNKNOWN
Requires-Python: >=3.9
